{
  "title": "Chess Fundamentals #2: Coordination",
  "description": "John Bartholomew's Chess Fundamentals #2 on piece coordination: two live chess.com games and an endgame lesson on developing your forces, limiting pawn moves, and the knight-c-pawn relationship.",
  "source_url": "https://www.youtube.com/watch?v=TWJ6751RRis",
  "kind": "lesson",
  "duration_minutes": 52,
  "date": "2015-01-04",
  "published": "2026-05-31T19:08:20Z",
  "slug": "chess-fundamentals-piece-coordination",
  "video_date": "2015-01-04",
  "views": 634776,
  "tags": [
    "chess"
  ]
}
